OAIParser/__init__.py
OAIParser-0.1.dist-info/LICENSE
OAIParser-0.1.dist-info/METADATA
OAIParser-0.1.dist-info/WHEEL
OAIParser-0.1.dist-info/top_level.txt
OAIParser-0.1.dist-info/RECORD
