Metadata-Version: 2.1
Name: OAIParser
Version: 0.1
Summary: An Open API parser for hydrus by HTTP-APIs
Home-page: https://github.com/de-sh/OAIParser
Author: Devdutt Shenoi
Author-email: devdutt@outlook.in
License: UNKNOWN
Platform: UNKNOWN
Classifier: Programming Language :: Python :: 3
Classifier: License :: OSI Approved :: MIT License
Classifier: Operating System :: OS Independent
